Workbook
Name Region: '📦 Raw Data'!$E:$E
Name Revenue: '📦 Raw Data'!$K:$K
Name SalesData: '📦 Raw Data'!$A$1:$P$301
Name Slicer_Category: #N/A
Name Slicer_Region: #N/A

Sheet 📦 Raw Data
A1: Order ID | B1: Date | C1: Month | D1: Quarter | E1: Region | F1: Category | G1: Product | H1: Sales Rep | I1: Unit Price | J1: Units Sold | K1: Revenue | L1: Discount % | M1: Net Revenue | N1: Cost | O1: Profit | P1: Profit Margin %
A2: ORD-0001 | B2: 45234 | C2: Nov | D2: Q4 | E2: North | F2: Office Supplies | G2: Pens Set | H2: David Lee | I2: 4.85 | J2: 4 | K2: =I2*J2 -> 19.4 | L2: 0 | M2: =K2*(1-L2/100) -> 19.4 | N2: 11.59 | O2: =M2-N2 -> 7.81 | P2: =IF(M2=0,0,O2/M2) -> 0.40257732
A3: ORD-0002 | B3: 44927 | C3: Jan | D3: Q1 | E3: North | F3: Furniture | G3: Chair | H3: Alice Johnson | I3: 177.09 | J3: 23 | K3: =I3*J3 -> 4073.07 | L3: 0.15 | M3: =K3*(1-L3/100) -> 4066.9604 | N3: 2057.39 | O3: =M3-N3 -> 2009.5704 | P3: =IF(M3=0,0,O3/M3) -> 0.49412097
A4: ORD-0003 | B4: 45208 | C4: Oct | D4: Q4 | E4: North | F4: Furniture | G4: Cabinet | H4: Frank Wilson | I4: 207.79 | J4: 7 | K4: =I4*J4 -> 1454.53 | L4: 0.1 | M4: =K4*(1-L4/100) -> 1453.0755 | N4: 691.7 | O4: =M4-N4 -> 761.37547 | P4: =IF(M4=0,0,O4/M4) -> 0.52397517
A5: ORD-0004 | B5: 45111 | C5: Jul | D5: Q3 | E5: East | F5: Office Supplies | G5: Folders | H5: Emma Davis | I5: 7.82 | J5: 24 | K5: =I5*J5 -> 187.68 | L5: 0.2 | M5: =K5*(1-L5/100) -> 187.30464 | N5: 109.64 | O5: =M5-N5 -> 77.66464 | P5: =IF(M5=0,0,O5/M5) -> 0.41464344
A6: ORD-0005 | B6: 45110 | C6: Jul | D6: Q3 | E6: East | F6: Sports | G6: Tennis Racket | H6: David Lee | I6: 68.88 | J6: 2 | K6: =I6*J6 -> 137.76 | L6: 0.05 | M6: =K6*(1-L6/100) -> 137.69112 | N6: 88.61 | O6: =M6-N6 -> 49.08112 | P6: =IF(M6=0,0,O6/M6) -> 0.35645814
A7: ORD-0006 | B7: 44985 | C7: Feb | D7: Q1 | E7: South | F7: Electronics | G7: Headphones | H7: Emma Davis | I7: 56.34 | J7: 27 | K7: =I7*J7 -> 1521.18 | L7: 0.1 | M7: =K7*(1-L7/100) -> 1519.6588 | N7: 746.32 | O7: =M7-N7 -> 773.33882 | P7: =IF(M7=0,0,O7/M7) -> 0.50888977
A8: ORD-0007 | B8: 45084 | C8: Jun | D8: Q2 | E8: East | F8: Electronics | G8: Webcam | H8: Carol White | I8: 46.68 | J8: 8 | K8: =I8*J8 -> 373.44 | L8: 0 | M8: =K8*(1-L8/100) -> 373.44 | N8: 211.22 | O8: =M8-N8 -> 162.22 | P8: =IF(M8=0,0,O8/M8) -> 0.43439374
A9: ORD-0008 | B9: 45067 | C9: May | D9: Q2 | E9: South | F9: Office Supplies | G9: Notebook | H9: David Lee | I9: 10.49 | J9: 26 | K9: =I9*J9 -> 272.74 | L9: 0.1 | M9: =K9*(1-L9/100) -> 272.46726 | N9: 150.05 | O9: =M9-N9 -> 122.41726 | P9: =IF(M9=0,0,O9/M9) -> 0.44929163
A10: ORD-0009 | B10: 44964 | C10: Feb | D10: Q1 | E10: East | F10: Furniture | G10: Cabinet | H10: Grace Kim | I10: 268.47 | J10: 21 | K10: =I10*J10 -> 5637.87 | L10: 0.2 | M10: =K10*(1-L10/100) -> 5626.5943 | N10: 2738.4 | O10: =M10-N10 -> 2888.1943 | P10: =IF(M10=0,0,O10/M10) -> 0.51331127
A11: ORD-0010 | B11: 44993 | C11: Mar | D11: Q1 | E11: East | F11: Sports | G11: Jump Rope | H11: Grace Kim | I11: 10.81 | J11: 5 | K11: =I11*J11 -> 54.05 | L11: 0.2 | M11: =K11*(1-L11/100) -> 53.9419 | N11: 25.55 | O11: =M11-N11 -> 28.3919 | P11: =IF(M11=0,0,O11/M11) -> 0.52634223
A12: ORD-0011 | B12: 44954 | C12: Jan | D12: Q1 | E12: North | F12: Furniture | G12: Chair | H12: Grace Kim | I12: 179.73 | J12: 13 | K12: =I12*J12 -> 2336.49 | L12: 0.15 | M12: =K12*(1-L12/100) -> 2332.9853 | N12: 1399.5 | O12: =M12-N12 -> 933.48526 | P12: =IF(M12=0,0,O12/M12) -> 0.4001248
A13: ORD-0012 | B13: 45155 | C13: Aug | D13: Q3 | E13: East | F13: Sports | G13: Yoga Mat | H13: Bob Martinez | I13: 31.02 | J13: 18 | K13: =I13*J13 -> 558.36 | L13: 0.05 | M13: =K13*(1-L13/100) -> 558.08082 | N13: 358.57 | O13: =M13-N13 -> 199.51082 | P13: =IF(M13=0,0,O13/M13) -> 0.35749449
... A15: ORD-0014 | B15: 45002 | C15: Mar | D15: Q1 | E15: North | F15: Office Supplies | G15: Folders | H15: David Lee | I15: 5.86 | J15: 25 | K15: =I15*J15 -> 146.5 | L15: 0 | M15: =K15*(1-L15/100) -> 146.5 | N15: 85.66 | O15: =M15-N15 -> 60.84 | P15: =IF(M15=0,0,O15/M15) -> 0.4152901
A16: ORD-0015 | B16: 45170 | C16: Sep | D16: Q3 | E16: East | F16: Clothing | G16: T-Shirt | H16: Bob Martinez | I16: 20.47 | J16: 29 | K16: =I16*J16 -> 593.63 | L16: 0.05 | M16: =K16*(1-L16/100) -> 593.33319 | N16: 302.64 | O16: =M16-N16 -> 290.69319 | P16: =IF(M16=0,0,O16/M16) -> 0.48993246 | S16: =SUM(O2:O301) -> 141821.48
A17: ORD-0016 | B17: 45035 | C17: Apr | D17: Q2 | E17: North | F17: Electronics | G17: Headphones | H17: Bob Martinez | I17: 69.45 | J17: 18 | K17: =I17*J17 -> 1250.1 | L17: 0 | M17: =K17*(1-L17/100) -> 1250.1 | N17: 602.67 | O17: =M17-N17 -> 647.43 | P17: =IF(M17=0,0,O17/M17) -> 0.51790257
A18: ORD-0017 | B18: 45156 | C18: Aug | D18: Q3 | E18: South | F18: Office Supplies | G18: Folders | H18: Grace Kim | I18: 8.29 | J18: 30 | K18: =I18*J18 -> 248.7 | L18: 0.05 | M18: =K18*(1-L18/100) -> 248.57565 | N18: 156.3 | O18: =M18-N18 -> 92.27565 | P18: =IF(M18=0,0,O18/M18) -> 0.37121758
A19: ORD-0018 | B19: 45129 | C19: Jul | D19: Q3 | E19: East | F19: Clothing | G19: Hat | H19: Henry Brown | I19: 17.29 | J19: 8 | K19: =I19*J19 -> 138.32 | L19: 0 | M19: =K19*(1-L19/100) -> 138.32 | N19: 73.93 | O19: =M19-N19 -> 64.39 | P19: =IF(M19=0,0,O19/M19) -> 0.46551475
A20: ORD-0019 | B20: 45217 | C20: Oct | D20: Q4 | E20: South | F20: Sports | G20: Dumbbells | H20: Alice Johnson | I20: 37.42 | J20: 21 | K20: =I20*J20 -> 785.82 | L20: 0 | M20: =K20*(1-L20/100) -> 785.82 | N20: 398.59 | O20: =M20-N20 -> 387.23 | P20: =IF(M20=0,0,O20/M20) -> 0.49277188
A21: ORD-0020 | B21: 44954 | C21: Jan | D21: Q1 | E21: East | F21: Electronics | G21: Webcam | H21: David Lee | I21: 41.57 | J21: 16 | K21: =I21*J21 -> 665.12 | L21: 0.05 | M21: =K21*(1-L21/100) -> 664.78744 | N21: 388.96 | O21: =M21-N21 -> 275.82744 | P21: =IF(M21=0,0,O21/M21) -> 0.41491073
A22: ORD-0021 | B22: 45279 | C22: Dec | D22: Q4 | E22: West | F22: Furniture | G22: Cabinet | H22: Grace Kim | I22: 199.04 | J22: 4 | K22: =I22*J22 -> 796.16 | L22: 0.15 | M22: =K22*(1-L22/100) -> 794.96576 | N22: 428.79 | O22: =M22-N22 -> 366.17576 | P22: =IF(M22=0,0,O22/M22) -> 0.46061828
A23: ORD-0022 | B23: 45122 | C23: Jul | D23: Q3 | E23: North | F23: Electronics | G23: Laptop | H23: Grace Kim | I23: 252.82 | J23: 26 | K23: =I23*J23 -> 6573.32 | L23: 0 | M23: =K23*(1-L23/100) -> 6573.32 | N23: 3366.64 | O23: =M23-N23 -> 3206.68 | P23: =IF(M23=0,0,O23/M23) -> 0.48783263
A24: ORD-0023 | B24: 45034 | C24: Apr | D24: Q2 | E24: West | F24: Furniture | G24: Cabinet | H24: Carol White | I24: 207.85 | J24: 8 | K24: =I24*J24 -> 1662.8 | L24: 0 | M24: =K24*(1-L24/100) -> 1662.8 | N24: 932.49 | O24: =M24-N24 -> 730.31 | P24: =IF(M24=0,0,O24/M24) -> 0.43920496
A25: ORD-0024 | B25: 45173 | C25: Sep | D25: Q3 | E25: North | F25: Sports | G25: Yoga Mat | H25: Bob Martinez | I25: 34.08 | J25: 28 | K25: =I25*J25 -> 954.24 | L25: 0.05 | M25: =K25*(1-L25/100) -> 953.76288 | N25: 469.08 | O25: =M25-N25 -> 484.68288 | P25: =IF(M25=0,0,O25/M25) -> 0.50817964
A26: ORD-0025 | B26: 45154 | C26: Aug | D26: Q3 | E26: South | F26: Clothing | G26: T-Shirt | H26: Carol White | I26: 16.34 | J26: 13 | K26: =I26*J26 -> 212.42 | L26: 0.05 | M26: =K26*(1-L26/100) -> 212.31379 | N26: 144.81 | O26: =M26-N26 -> 67.50379 | P26: =IF(M26=0,0,O26/M26) -> 0.3179435
A27: ORD-0026 | B27: 45148 | C27: Aug | D27: Q3 | E27: West | F27: Sports | G27: Jump Rope | H27: Carol White | I27: 9.95 | J27: 7 | K27: =I27*J27 -> 69.65 | L27: 0 | M27: =K27*(1-L27/100) -> 69.65 | N27: 41.43 | O27: =M27-N27 -> 28.22 | P27: =IF(M27=0,0,O27/M27) -> 0.4051687
A28: ORD-0027 | B28: 45171 | C28: Sep | D28: Q3 | E28: East | F28: Electronics | G28: Laptop | H28: Henry Brown | I28: 230.29 | J28: 28 | K28: =I28*J28 -> 6448.12 | L28: 0 | M28: =K28*(1-L28/100) -> 6448.12 | N28: 2993.28 | O28: =M28-N28 -> 3454.84 | P28: =IF(M28=0,0,O28/M28) -> 0.53579028
... A301: ORD-0300 | B301: 45159 | C301: Aug | D301: Q3 | E301: East | F301: Electronics | G301: Webcam | H301: Grace Kim | I301: 40.36 | J301: 14 | K301: =I301*J301 -> 565.04 | L301: 0.05 | M301: =K301*(1-L301/100) -> 564.75748 | N301: 324.12 | O301: =M301-N301 -> 240.63748 | P301: =IF(M301=0,0,O301/M301) -> 0.42608994

Sheet 📋 Tasks & Guide
A1: 🛒 Superstore Sales Analysis — Excel Skills Evaluation
A2: Dataset: 300 orders | 2023 | 5 product categories | 4 regions | 8 sales reps — Complete all 10 tasks in the '✏️ Your Work' sheet
A3: # | B3: Task | C3: Instructions | D3: Skills Tested | E3: Points
A4: 1 | B4: Data Cleaning & Formatting | C4: On the Raw Data sheet: • Format the 'Date' column as DD-MMM-YYYY • Format Revenue, Net Revenue, Cost, Profit as currency ($) • Apply conditional formatting: colour Profit Margin % red if <40%, green if ≥40% • Bold the header row and freeze it | D4: Formatting, Conditional Formatting | E4: 10 pts | F4: ok
A5: 2 | B5: Named Ranges | C5: Create named ranges for key columns: • SalesData = entire table (A1:P301) • Revenue = column K (K2:K301) • Region = column E (E2:E301) Use Formulas → Name Manager | D5: Named Ranges | E5: 5 pts | F5: ok
A6: 3 | B6: Formula Corner | C6: In the 'Your Work' sheet, use formulas to calculate: • Total Revenue (SUM) • Average Profit Margin % (AVERAGE) • Highest single-order Revenue (MAX) • Count of orders with Discount > 0 (COUNTIF) • Total Revenue from the 'Electronics' category (SUMIF) | D6: SUM, AVERAGE, MAX, COUNTIF, SUMIF | E6: 15 pts | F6: ok
A7: 4 | B7: VLOOKUP / XLOOKUP | C7: In the 'Your Work' sheet: • Build a lookup table: given an Order ID (e.g. ORD-0042), return the Sales Rep, Product, and Net Revenue using VLOOKUP or XLOOKUP • Add data validation on the Order ID input cell (list or text length) | D7: VLOOKUP / XLOOKUP, Data Validation | E7: 15 pts | F7: ok
A8: 5 | B8: PivotTable — Sales by Region & Category | C8: Insert a PivotTable on a new sheet named 'Pivot – Region': • Rows: Region | Columns: Category • Values: Sum of Net Revenue (formatted as $#,##0) • Add a Grand Total row and column • Apply a PivotTable style (Medium 9 or similar) | D8: PivotTable, Grouping, Formatting | E8: 15 pts | F8: ok
A9: 6 | B9: PivotTable — Monthly Trend | C9: Insert a second PivotTable on a sheet named 'Pivot – Monthly': • Rows: Month (Jan–Dec in order) • Values: Sum of Revenue, Sum of Profit, Average Profit Margin % • Add a calculated field: 'Avg Order Value' = Revenue / 300 (Hint: sort months manually or use a helper column with month numbers) | D9: PivotTable, Calculated Field, Sorting | E9: 15 pts | F9: ok
A10: 7 | B10: Chart — Bar Chart | C10: From your Region PivotTable, create a Clustered Bar Chart: • Title: 'Net Revenue by Region & Category' • Add data labels • Use a professional colour scheme (match the region colours) • Place the chart on the 'Pivot – Region' sheet | D10: Bar Chart, Chart Formatting | E10: 10 pts | F10: ok
A11: 8 | B11: Chart — Line Chart | C11: From your Monthly PivotTable, create a Line Chart with two series: • Revenue (primary axis, left) • Profit Margin % (secondary axis, right) • Title: '2023 Monthly Revenue & Profit Margin' • Add axis titles • Place on 'Pivot – Monthly' sheet | D11: Line Chart, Dual Axis, Chart Formatting | E11: 10 pts | F11: ok
A12: 9 | B12: Dashboard KPI Tiles | C12: In the 'Your Work' sheet, build 4 KPI tiles (use merged cells + formulas): ① Total Revenue ② Total Profit ③ Avg Profit Margin % ④ Best-Performing Region (use INDEX/MATCH on pivot data) Style each tile with a coloured background and large bold number | D12: INDEX/MATCH, Design, Cell Formatting | E12: 15 pts | F12: ok
A13: 10 | B13: Slicer & Final Polish | C13: Add Slicers to both PivotTables (Region and Category slicers). Connect the Category slicer to BOTH PivotTables simultaneously. Finally: • Add a sheet named '📊 Dashboard' that summarises your KPI tiles and both charts on one screen • Name the workbook tab colours (right-click → Tab Color) | D13: Slicers, Slicer Connections, Dashboard Layout | E13: 20 pts
A14: TOTAL POINTS | E14: 130 pts
A16: 📊 Scoring Guide
A17: Score | B17: Grade | C17: What it means
A18: 117–130 | B18: 90%+ | C18: ⭐⭐⭐ Excel Expert — you're ready for analyst-level work
A19: 91–116 | B19: 70–89% | C19: ⭐⭐ Proficient — solid intermediate skills, a few gaps to close
A20: 65–90 | B20: 50–69% | C20: ⭐ Developing — good foundation, revisit PivotTables and charts
A21: < 65 | B21: < 50% | C21: 📚 Keep Practising — focus on Tasks 3–6 first

Sheet DASHBOARD
A1: SUPERSTORE SALES DASHBOARD
A4: ="Total Revenue: " & CHAR(10) &SUM(Revenue) -> Total Revenue: 332345.98 | F4: ="Total Profit: "&CHAR(10) &ROUNDUP(SUM('📦 Raw Data'!O2:O301),2) -> Total Profit: 141821.49 | K4: ="Average Profit Margin%: "&CHAR(10) &ROUNDUP(AVERAGE('📦 Raw Data'!P:P)*100, 2) -> Average Profit Margin%: 42.64 | P4: ="Best Region base on total Net Revenue: "&CHAR(10)&INDEX('Pivot-Region'!$A$3:$A$6, MATCH(MAX('Pivot-Region'!$G$3:$G$6),'Pivot-Region'!$G$3:$G$6,0)) -> Best Region base on total Net Revenue: East
A29: Sum of Net Revenue | B29: Column Labels | I29: Row Labels | J29: Sum of Revenue | K29: Average of Profit Margin %
A30: Row Labels | B30: Clothing | C30: Electronics | D30: Furniture | E30: Office Supplies | F30: Sports | G30: Grand Total | I30: Jan | J30: 28908.13 | K30: 0.45097754
A31: East | B31: 14642.93 | C31: 28668.697 | D31: 59877.44 | E31: 2981.4247 | F31: 6372.2163 | G31: 112542.71 | I31: Feb | J31: 26306.09 | K31: 0.43041392
A32: North | B32: 11952.768 | C32: 29454.817 | D32: 32974.454 | E32: 3962.292 | F32: 9396.6765 | G32: 87741.007 | I32: Mar | J32: 16746.13 | K32: 0.42141265
A33: South | B33: 13036.211 | C33: 10344.192 | D33: 39915.169 | E33: 3557.4496 | F33: 5303.2134 | G33: 72156.234 | I33: Apr | J33: 40373.99 | K33: 0.4399735
A34: West | B34: 14215.539 | C34: 15139.796 | D34: 20505.33 | E34: 1893.3815 | F34: 7898.1284 | G34: 59652.175 | I34: May | J34: 26745.14 | K34: 0.43865976
A35: Grand Total | B35: 53847.448 | C35: 83607.502 | D35: 153272.39 | E35: 12394.548 | F35: 28970.235 | G35: 332092.12 | I35: Jun | J35: 34041.39 | K35: 0.42960588
I36: Jul | J36: 26481.05 | K36: 0.42605106
I37: Aug | J37: 17386.37 | K37: 0.39354116
I38: Sep | J38: 28688.86 | K38: 0.42981045
I39: Oct | J39: 35307.23 | K39: 0.41682825
I40: Nov | J40: 12264.2 | K40: 0.44771467
I41: Dec | J41: 39097.4 | K41: 0.39360397
I42: Grand Total | J42: 332345.98 | K42: 0.42630853

Sheet Pivot-Region
A1: Sum of Net Revenue | B1: Column Labels
A2: Row Labels | B2: Clothing | C2: Electronics | D2: Furniture | E2: Office Supplies | F2: Sports | G2: Grand Total
A3: East | B3: 14642.93 | C3: 28668.697 | D3: 59877.44 | E3: 2981.4247 | F3: 6372.2163 | G3: 112542.71
A4: North | B4: 11952.768 | C4: 29454.817 | D4: 32974.454 | E4: 3962.292 | F4: 9396.6765 | G4: 87741.007
A5: South | B5: 13036.211 | C5: 10344.192 | D5: 39915.169 | E5: 3557.4496 | F5: 5303.2134 | G5: 72156.234
A6: West | B6: 14215.539 | C6: 15139.796 | D6: 20505.33 | E6: 1893.3815 | F6: 7898.1284 | G6: 59652.175
A7: Grand Total | B7: 53847.448 | C7: 83607.502 | D7: 153272.39 | E7: 12394.548 | F7: 28970.235 | G7: 332092.12

Sheet Pivot-Monthly
A3: Date | B3: (All)
A5: Row Labels | B5: Sum of Revenue | C5: Average of Profit Margin %
A6: Jan | B6: 28908.13 | C6: 0.45097754
A7: Feb | B7: 26306.09 | C7: 0.43041392
A8: Mar | B8: 16746.13 | C8: 0.42141265
A9: Apr | B9: 40373.99 | C9: 0.4399735
A10: May | B10: 26745.14 | C10: 0.43865976
A11: Jun | B11: 34041.39 | C11: 0.42960588
A12: Jul | B12: 26481.05 | C12: 0.42605106
A13: Aug | B13: 17386.37 | C13: 0.39354116
A14: Sep | B14: 28688.86 | C14: 0.42981045
A15: Oct | B15: 35307.23 | C15: 0.41682825
A16: Nov | B16: 12264.2 | C16: 0.44771467
A17: Dec | B17: 39097.4 | C17: 0.39360397
A18: Grand Total | B18: 332345.98 | C18: 0.42630853

Sheet Work
A1: ✏️ Your Work — Complete your formulas and analyses here
A3: Formula Corner
A4: Total Revenue | B4: =SUM(Revenue) -> 332345.98
A5: Average Profit Margin % | B5: =ROUNDUP(AVERAGE('📦 Raw Data'!P:P)*100, 2) -> 42.64
A6: Highest Single-Order Revenue | B6: =MAX(Revenue) -> 7701.68
A7: Orders with Discount > 10% | B7: =COUNTIF('📦 Raw Data'!L:L, ">10%") -> 80
A8: Electronics Revenue | B8: =SUMIF('📦 Raw Data'!F:F, "Electronics",Revenue) -> 83660.23
A10: VLOOKUP / XLOOKUP
A11: Order ID Input | B11: ORD-0042
A12: Sales Rep | B12: =VLOOKUP(B11,SalesData,8, FALSE) -> Grace Kim
A13: Product | B13: =VLOOKUP(B11, SalesData,7,FALSE) -> Folders
A14: Net Revenue | B14: =VLOOKUP(B11,SalesData,13,FALSE) -> 200.67912
A17: KPI Dashboard Tiles
B19: ="Total Revenue: " & SUM(Revenue) -> Total Revenue: 332345.98
B22: ="Total Profit: "&ROUNDUP(SUM('📦 Raw Data'!O2:O301),2) -> Total Profit: 141821.49
B25: ="Average Profit Margin%: "&ROUNDUP(AVERAGE('📦 Raw Data'!P:P)*100, 2) -> Average Profit Margin%: 42.64
B28: ="Best Region base on total Net Revenue: "&INDEX('Pivot-Region'!$A$3:$A$6, MATCH(MAX('Pivot-Region'!$G$3:$G$6),'Pivot-Region'!$G$3:$G$6,0)) -> Best Region base on total Net Revenue: East

Sheet 📖 Data Dictionary
A1: 📖 Data Dictionary — Superstore Sales Dataset
A2: Column | B2: Data Type | C2: Description | D2: Example
A3: Order ID | B3: Text | C3: Unique identifier for each order | D3: ORD-0001
A4: Date | B4: Date | C4: Order date (DD-MMM-YYYY after formatting) | D4: 15-Mar-2023
A5: Month | B5: Text | C5: Abbreviated month name | D5: Mar
A6: Quarter | B6: Text | C6: Fiscal quarter of the order | D6: Q1
A7: Region | B7: Text | C7: Sales region (North/South/East/West) | D7: North
A8: Category | B8: Text | C8: Product category (5 categories) | D8: Electronics
A9: Product | B9: Text | C9: Product name | D9: Laptop
A10: Sales Rep | B10: Text | C10: Name of the sales representative | D10: Alice Johnson
A11: Unit Price | B11: Currency | C11: Price per single unit ($) | D11: $234.50
A12: Units Sold | B12: Number | C12: Quantity of units in the order | D12: 12
A13: Revenue | B13: Currency | C13: Gross revenue = Unit Price × Units Sold | D13: $2,814.00
... A18: Profit Margin % | B18: Percentage | C18: Profit ÷ Net Revenue × 100 | D18: 44.5%
